NAbleAPI/__init__.py
NAbleAPI/client.py
NAbleAPI/exceptions.py
NAbleAPI-0.0.9.dist-info/LICENSE.md
NAbleAPI-0.0.9.dist-info/METADATA
NAbleAPI-0.0.9.dist-info/WHEEL
NAbleAPI-0.0.9.dist-info/top_level.txt
NAbleAPI-0.0.9.dist-info/RECORD
