Metadata-Version: 2.2
Name: NAbleAPI
Version: 0.0.9
Summary: NAble Data Extraction API library/wrapper
Author-email: Fryan O <FryanO@proton.me>
Project-URL: Homepage, https://github.com/ItsJustAGitHubMichealWhosGonnaSeeIt5Ppl/Python-NAbleAPI
Project-URL: Issues, https://github.com/ItsJustAGitHubMichealWhosGonnaSeeIt5Ppl/Python-NAbleAPI/issues
Project-URL: Documentation, https://python-nableapi.readthedocs.io/
Project-URL: Changelog, https://github.com/ItsJustAGitHubMichealWhosGonnaSeeIt5Ppl/Python-NAbleAPI/blob/main/CHANGELOG.md
Keywords: NAble,NSight,N-Able,N-Sight,Solarwinds,Solar Winds
Classifier: Programming Language :: Python :: 3
Classifier: License :: OSI Approved :: GNU Affero General Public License v3
Classifier: Operating System :: OS Independent
Classifier: Development Status :: 2 - Pre-Alpha
Requires-Python: >=3.12
License-File: LICENSE.md
Requires-Dist: certifi>=2024.8.30
Requires-Dist: charset-normalizer>=3.4.0
Requires-Dist: idna>=3.10
Requires-Dist: requests>=2.32.3
Requires-Dist: urllib3>=2.2.3
Requires-Dist: xmltodict>=0.14.2
